portable_spreadsheet/__init__.py
portable_spreadsheet/cell.py
portable_spreadsheet/cell_indices.py
portable_spreadsheet/cell_indices_templates.py
portable_spreadsheet/cell_slice.py
portable_spreadsheet/cell_type.py
portable_spreadsheet/grammar_utils.py
portable_spreadsheet/grammars.py
portable_spreadsheet/serialization.py
portable_spreadsheet/serialization_interface.py
portable_spreadsheet/sheet.py
portable_spreadsheet/sheet_utils.py
portable_spreadsheet/skipped_label.py
portable_spreadsheet/utils.py
portable_spreadsheet/word_constructor.py
portable_spreadsheet/work_book.py
tests/__init__.py
tests/test_cell_word_constructor.py
tests/test_grammar_utils.py
tests/test_serialization.py
tests/test_spreadsheet.py
tests/test_workbook.py
portable_spreadsheet-2.2.1.dist-info/LICENSE
portable_spreadsheet-2.2.1.dist-info/METADATA
portable_spreadsheet-2.2.1.dist-info/WHEEL
portable_spreadsheet-2.2.1.dist-info/top_level.txt
portable_spreadsheet-2.2.1.dist-info/RECORD
