Metadata-Version: 2.1
Name: portable-spreadsheet
Version: 2.2.1
Summary: A simple spreadsheet that keeps tracks of each operation of each cell in defined languages. Logic allows exporting sheets to Excel files (and see how each cell is computed), to the JSON strings with a description of computation of each cell (e. g. in the native language). Other formats, like HTML, CSV and Markdown (MD), are also implemented (user can define own format). It also allows reconstructing behaviours in native Python with NumPy.
Home-page: https://github.com/david-salac/Portable-spreadsheet-generator
Author: David Salac
Author-email: info@davidsalac.eu
License: UNKNOWN
Platform: UNKNOWN
Classifier: Programming Language :: Python :: 3
Classifier: License :: OSI Approved :: MIT License
Classifier: Operating System :: OS Independent
Requires-Python: >=3.8
Requires-Dist: numpy
Requires-Dist: numpy-financial
Requires-Dist: XlsxWriter
